inventree_digikey_integration/ConfigReader.py
inventree_digikey_integration/Digikey.py
inventree_digikey_integration/ImageManager.py
inventree_digikey_integration/Inventree.py
inventree_digikey_integration/__init__.py
inventree_digikey_integration/__main__.py
inventree_digikey_integration-1.0.0.dist-info/LICENSE
inventree_digikey_integration-1.0.0.dist-info/METADATA
inventree_digikey_integration-1.0.0.dist-info/WHEEL
inventree_digikey_integration-1.0.0.dist-info/entry_points.txt
inventree_digikey_integration-1.0.0.dist-info/RECORD
