Metadata-Version: 2.1
Name: inventree_digikey_integration
Version: 1.0.0
Summary: A CLI to import Digikey parts into an Inventree instance
License: MIT
Author: Eric Udlis
Author-email: udlis.eric@gmail.com
Requires-Python: >=3.8,<4.0
Classifier: License :: OSI Approved :: MIT License
Classifier: Programming Language :: Python :: 3
Classifier: Programming Language :: Python :: 3.8
Classifier: Programming Language :: Python :: 3.9
Classifier: Programming Language :: Python :: 3.10
Classifier: Programming Language :: Python :: 3.11
Classifier: Programming Language :: Python :: 3.12
Requires-Dist: digikey-api (>=1.0.0,<2.0.0)
Requires-Dist: inventree (>=0.13.1,<0.14.0)
